{"nodes": [{"id": "a_projects_8_attandance_src_pages_admin_config_jsx", "label": "Config.jsx", "file_type": "code", "source_file": "A:\\projects\\8.attandance\\src\\pages\\admin\\Config.jsx", "source_location": "L1"}, {"id": "config_adminconfig", "label": "AdminConfig()", "file_type": "code", "source_file": "A:\\projects\\8.attandance\\src\\pages\\admin\\Config.jsx", "source_location": "L6"}], "edges": [{"source": "a_projects_8_attandance_src_pages_admin_config_jsx", "target": "react", "relation": "imports_from", "confidence": "EXTRACTED", "source_file": "A:\\projects\\8.attandance\\src\\pages\\admin\\Config.jsx", "source_location": "L1", "weight": 1.0}, {"source": "a_projects_8_attandance_src_pages_admin_config_jsx", "target": "a_projects_8_attandance_src_components_ui_systemsettingsform", "relation": "imports_from", "confidence": "EXTRACTED", "source_file": "A:\\projects\\8.attandance\\src\\pages\\admin\\Config.jsx", "source_location": "L2", "weight": 1.0}, {"source": "a_projects_8_attandance_src_pages_admin_config_jsx", "target": "lucide_react", "relation": "imports_from", "confidence": "EXTRACTED", "source_file": "A:\\projects\\8.attandance\\src\\pages\\admin\\Config.jsx", "source_location": "L3", "weight": 1.0}, {"source": "a_projects_8_attandance_src_pages_admin_config_jsx", "target": "a_projects_8_attandance_src_components_ui_button", "relation": "imports_from", "confidence": "EXTRACTED", "source_file": "A:\\projects\\8.attandance\\src\\pages\\admin\\Config.jsx", "source_location": "L4", "weight": 1.0}, {"source": "a_projects_8_attandance_src_pages_admin_config_jsx", "target": "config_adminconfig", "relation": "contains", "confidence": "EXTRACTED", "source_file": "A:\\projects\\8.attandance\\src\\pages\\admin\\Config.jsx", "source_location": "L6", "weight": 1.0}], "raw_calls": []}